google_adk_quercle/__init__.py
google_adk_quercle/py.typed
google_adk_quercle/tools.py
google_adk_quercle-0.1.0.dist-info/METADATA
google_adk_quercle-0.1.0.dist-info/WHEEL
google_adk_quercle-0.1.0.dist-info/licenses/LICENSE
google_adk_quercle-0.1.0.dist-info/RECORD
